sage_wheels/bin/points2allfinetriangs
sage_wheels/bin/points2mintriang
sage_wheels/bin/B_A_center
sage_wheels/bin/cyclic
sage_wheels/bin/kDn
sage_wheels/bin/chiro2nallfinetriangs
sage_wheels/bin/chiro2ntriangs
sage_wheels/bin/Dnxk
sage_wheels/bin/points2triangs
sage_wheels/bin/points2prettyprint
sage_wheels/bin/points2finetriangs
sage_wheels/bin/chiro2finetriangs
sage_wheels/bin/points2nallfinetriangs
sage_wheels/bin/points2circuits
sage_wheels/bin/chiro2dual
sage_wheels/bin/checkregularity
sage_wheels/bin/points2gale
sage_wheels/bin/binomial
sage_wheels/bin/chiro2nfinetriangs
sage_wheels/bin/points2nflips
sage_wheels/bin/chiro2ncocircuits
sage_wheels/bin/points2symmetries
sage_wheels/bin/points2placingtriang
sage_wheels/bin/points2ncircuits
sage_wheels/bin/B_S_center
sage_wheels/bin/cube
sage_wheels/bin/points2ntriangs
sage_wheels/bin/points2alltriangs
sage_wheels/bin/cross
sage_wheels/bin/points2facets
sage_wheels/bin/B_S
sage_wheels/bin/B_A
sage_wheels/bin/chiro2circuits
sage_wheels/bin/chiro2alltriangs
sage_wheels/bin/points2flips
sage_wheels/bin/points2ncocircuits
sage_wheels/bin/points2vertices
sage_wheels/bin/chiro2allfinetriangs
sage_wheels/bin/lattice
sage_wheels/bin/cocircuits2facets
sage_wheels/bin/points2volume
sage_wheels/bin/points2nfinetriangs
sage_wheels/bin/santos_dim4_triang
sage_wheels/bin/santos_triang
sage_wheels/bin/chiro2ncircuits
sage_wheels/bin/santos_22_triang
sage_wheels/bin/points2chiro
sage_wheels/bin/chiro2placingtriang
sage_wheels/bin/permutahedron
sage_wheels/bin/points2finetriang
sage_wheels/bin/hypersimplex
sage_wheels/bin/points2nalltriangs
sage_wheels/bin/chiro2triangs
sage_wheels/bin/chiro2cocircuits
sage_wheels/bin/chiro2mintriang
sage_wheels/bin/check
sage_wheels/bin/chiro2nalltriangs
sage_wheels/bin/chiro2finetriang
sage_wheels/bin/points2cocircuits
sage_wheels/bin/B_D_center
sage_wheels/bin/B_D
passagemath_topcom-10.6.43.dist-info/RECORD
passagemath_topcom-10.6.43.dist-info/WHEEL
passagemath_topcom-10.6.43.dist-info/top_level.txt
passagemath_topcom-10.6.43.dist-info/METADATA
passagemath_topcom/__init__.py
